[{"DocumentTypeId":"Jetstream.NoCategory.Invoices","Keywords":[{"Values":["unit","price"],"NumberOfTimesConfirmed":1,"LastUpdated":"2022-05-23T17:07:52.3864085+01:00"},{"Values":["total","price"],"NumberOfTimesConfirmed":1,"LastUpdated":"2022-05-23T17:07:52.3865896+01:00"},{"Values":["quantiy","qty"],"NumberOfTimesConfirmed":1,"LastUpdated":"2022-05-23T17:07:52.3865916+01:00"},{"Values":["description"],"NumberOfTimesConfirmed":1,"LastUpdated":"2022-05-23T17:07:52.3865924+01:00"},{"Values":["total","amount"],"NumberOfTimesConfirmed":1,"LastUpdated":"2022-05-23T17:07:52.3865933+01:00"},{"Values":["total"],"NumberOfTimesConfirmed":1,"LastUpdated":"2022-05-23T17:07:52.3865942+01:00"}]}]
